Dans_Diffraction/__init__.py
Dans_Diffraction/__main__.py
Dans_Diffraction/classes_crystal.py
Dans_Diffraction/classes_fdmnes.py
Dans_Diffraction/classes_multicrystal.py
Dans_Diffraction/classes_orbitals.py
Dans_Diffraction/classes_orientation.py
Dans_Diffraction/classes_plotting.py
Dans_Diffraction/classes_properties.py
Dans_Diffraction/classes_scattering.py
Dans_Diffraction/classes_structures.py
Dans_Diffraction/functions_crystallography.py
Dans_Diffraction/functions_general.py
Dans_Diffraction/functions_lattice.py
Dans_Diffraction/functions_plotting.py
Dans_Diffraction/functions_scattering.py
Dans_Diffraction/multiple_scattering.py
Dans_Diffraction/tensor_scattering.py
Dans_Diffraction/Structures/Aluminium.cif
Dans_Diffraction/Structures/BCC.cif
Dans_Diffraction/Structures/Beryllium.cif
Dans_Diffraction/Structures/Ca2RuO4.cif
Dans_Diffraction/Structures/Ca3CoMnO6.mcif
Dans_Diffraction/Structures/Cobalt.cif
Dans_Diffraction/Structures/Copper.cif
Dans_Diffraction/Structures/Cubic.cif
Dans_Diffraction/Structures/Diamond.cif
Dans_Diffraction/Structures/FCC.cif
Dans_Diffraction/Structures/Gold.cif
Dans_Diffraction/Structures/Graphite.cif
Dans_Diffraction/Structures/HCP.cif
Dans_Diffraction/Structures/Iron.cif
Dans_Diffraction/Structures/KCl.cif
Dans_Diffraction/Structures/LaMnO3.mcif
Dans_Diffraction/Structures/LiCoO2.cif
Dans_Diffraction/Structures/MnO.mcif
Dans_Diffraction/Structures/Na0.8CoO2_P63mmc.cif
Dans_Diffraction/Structures/NaCoO2_stripe_supercell.cif
Dans_Diffraction/Structures/Niobium.cif
Dans_Diffraction/Structures/Ruby.cif
Dans_Diffraction/Structures/Ruthenium.cif
Dans_Diffraction/Structures/Rutile.cif
Dans_Diffraction/Structures/Sapphire.cif
Dans_Diffraction/Structures/Silicon.cif
Dans_Diffraction/Structures/Silver.cif
Dans_Diffraction/Structures/Sr3LiRuO6.cif
Dans_Diffraction/Structures/Sr3LiRuO6_C2'c'.mcif
Dans_Diffraction/Structures/Vanadium.cif
Dans_Diffraction/Structures/ZnO.cif
Dans_Diffraction/Structures/triclinic.cif
dans_diffraction-3.4.0.dist-info/licenses/LICENSE
dans_diffraction-3.4.0.dist-info/METADATA
dans_diffraction-3.4.0.dist-info/WHEEL
dans_diffraction-3.4.0.dist-info/entry_points.txt
dans_diffraction-3.4.0.dist-info/top_level.txt
dans_diffraction-3.4.0.dist-info/RECORD
