Metadata-Version: 2.4
Name: Dans_Diffraction
Version: 3.4.0
Summary: Generate diffracted intensities from crystals
Home-page: https://github.com/DanPorter/Dans_Diffraction
Author: Dan Porter
Author-email: Dan Porter <d.g.porter@outlook.com>
Maintainer-email: Dan Porter <d.g.porter@outlook.com>
License:                                  Apache License
Project-URL: Homepage, https://github.com/DanPorter/Dans_Diffraction
Project-URL: Documentation, https://danporter.github.io/Dans_Diffraction
Project-URL: Repository, https://github.com/DanPorter/Dans_Diffraction
Project-URL: Bug Tracker, https://github.com/DanPorter/Dans_Diffraction/issues
Project-URL: Changelog, https://github.com/DanPorter/Dans_Diffraction/blob/master/README.md
Keywords: crystal,cif,diffraction,crystallography,science,x-ray,neutron,resonant,magnetic,magnetism,multiple scattering,fdmnes,super structure,spacegroup,space group,diffractometer
Classifier: Programming Language :: Python :: 3.7
Classifier: Intended Audience :: Science/Research
Classifier: Topic :: Scientific/Engineering :: Physics
Classifier: License :: OSI Approved :: Apache Software License
Classifier: Development Status :: 3 - Alpha
Requires-Python: >=3.7
License-File: LICENSE
Requires-Dist: numpy
Requires-Dist: matplotlib
Dynamic: author
Dynamic: home-page
Dynamic: license-file
